setup.py
tiki/__init__.py
tiki/api.py
tiki/dict.txt
tiki/trie.py
tiki/utils.py
tiki.egg-info/PKG-INFO
tiki.egg-info/SOURCES.txt
tiki.egg-info/dependency_links.txt
tiki.egg-info/top_level.txt