Metadata-Version: 1.0
Name: tiki
Version: 0.2.0
Summary: Generate fancy names
Home-page: https://github.com/iloahz/tiki
Author: iloahz
Author-email: iloahz@gmail.com
License: Creative Commons Attribution 4.0 International License.
Platform: UNKNOWN
